github_snapshot/__init__.py
github_snapshot/arg_defaulter.py
github_snapshot/github_snapshot.py
github_snapshot/snapshot_purger.py
sqre_github_snapshot-0.2.1.dist-info/DESCRIPTION.rst
sqre_github_snapshot-0.2.1.dist-info/METADATA
sqre_github_snapshot-0.2.1.dist-info/RECORD
sqre_github_snapshot-0.2.1.dist-info/WHEEL
sqre_github_snapshot-0.2.1.dist-info/entry_points.txt
sqre_github_snapshot-0.2.1.dist-info/metadata.json
sqre_github_snapshot-0.2.1.dist-info/top_level.txt
