Metadata-Version: 2.0
Name: sqre-github-snapshot
Version: 0.2.1
Summary: LSST Data Management SQuaRE Github Organization Snapshotter
Home-page: https://github.com/lsst-sqre/sqre-github-snapshots/
Author: Adam Thornton
Author-email: athornton@lsst.org
License: MIT
Keywords: lsst
Platform: UNKNOWN
Classifier: Development Status :: 4 - Beta
Classifier: Programming Language :: Python :: 2.7
Classifier: License :: OSI Approved :: MIT License
Requires-Dist: MapGitConfig (==1.1)
Requires-Dist: awscli (==1.11.21)
Requires-Dist: github3.py (==1.0.0a4)
Requires-Dist: progressbar2 (==3.11.0)
Requires-Dist: requests (==2.8.1)
Requires-Dist: sqre-codekit (==1.0.1)
Requires-Dist: uritemplate.py (==2.0.0)
